omniblack/setup/__init__.py
omniblack/setup/gcc.py
omniblack.setup-0.1.4.dist-info/LICENSE.txt
omniblack.setup-0.1.4.dist-info/METADATA
omniblack.setup-0.1.4.dist-info/WHEEL
omniblack.setup-0.1.4.dist-info/entry_points.txt
omniblack.setup-0.1.4.dist-info/omniblack_package.json
omniblack.setup-0.1.4.dist-info/top_level.txt
omniblack.setup-0.1.4.dist-info/RECORD
