Metadata-Version: 2.1
Name: omniblack.setup
Version: 0.1.4
Summary: Library that helps package omniblack packages.
Author-email: Terry Patterson <Terryp@wegrok.net>
License: 
Project-URL: Repository, https://gitlab.com/terryp/terry.git
Project-URL: Homepage, https://gitlab.com/terryp/terry/-/tree/next/tooling/setup
Classifier: Development Status :: 3 - Alpha
Classifier: Intended Audience :: Developers
License-File: LICENSE.txt
Requires-Dist: ruamel.yaml~=0.18
Requires-Dist: setuptools~=69.0
Requires-Dist: msgspec~=0.18
